pysqlake/__init__.py
pysqlake/cli.py
pysqlake-0.0.4.dist-info/METADATA
pysqlake-0.0.4.dist-info/WHEEL
pysqlake-0.0.4.dist-info/licenses/LICENSE
pysqlake-0.0.4.dist-info/RECORD
