Metadata-Version: 2.1
Name: pysqlake
Version: 0.0.4
Summary: Run Upsolver SQLake commands using Python
Project-URL: Homepage, https://github.com/pypa/sampleproject
Project-URL: Bug Tracker, https://github.com/pypa/sampleproject/issues
Author-email: David Aisenthal <david@upsolver.com>
License-File: LICENSE
Classifier: License :: OSI Approved :: MIT License
Classifier: Operating System :: OS Independent
Classifier: Programming Language :: Python :: 3
Requires-Python: >=3.10
Requires-Dist: upsolver-cli>=0.6.4
